[
 {
  "call": {
   "from": "0x0000000000000000000000000000000000010000",
   "to": "0xa647ff3c36cfab592509e13860ab8c4f28781a66",
   "nonce": 0,
   "value": "0x0",
   "gasLimit": 12500000,
   "gasPrice": "0x1",
   "gasFeeCap": "0x0",
   "gasTipCap": "0x0",
   "data": "0x0a9254e4",
   "dataAbiValues": {
    "methodSignature": "setUp()",
    "inputValues": []
   },
   "AccessList": null,
   "SkipNonceChecks": true,
   "SkipFromEOACheck": true
  },
  "blockNumberDelay": 2663,
  "blockTimestampDelay": 342921
 },
 {
  "call": {
   "from": "0x0000000000000000000000000000000000010000",
   "to": "0xa647ff3c36cfab592509e13860ab8c4f28781a66",
   "nonce": 1,
   "value": "0x0",
   "gasLimit": 12500000,
   "gasPrice": "0x1",
   "gasFeeCap": "0x0",
   "gasTipCap": "0x0",
   "data": "0x0a9254e4",
   "dataAbiValues": {
    "methodSignature": "setUp()",
    "inputValues": []
   },
   "AccessList": null,
   "SkipNonceChecks": true,
   "SkipFromEOACheck": true
  },
  "blockNumberDelay": 4,
  "blockTimestampDelay": 6
 },
 {
  "call": {
   "from": "0x0000000000000000000000000000000000020000",
   "to": "0xa647ff3c36cfab592509e13860ab8c4f28781a66",
   "nonce": 0,
   "value": "0x0",
   "gasLimit": 12500000,
   "gasPrice": "0x1",
   "gasFeeCap": "0x0",
   "gasTipCap": "0x0",
   "data": "0x0a9254e4",
   "dataAbiValues": {
    "methodSignature": "setUp()",
    "inputValues": []
   },
   "AccessList": null,
   "SkipNonceChecks": true,
   "SkipFromEOACheck": true
  },
  "blockNumberDelay": 1583,
  "blockTimestampDelay": 87769
 },
 {
  "call": {
   "from": "0x0000000000000000000000000000000000020000",
   "to": "0xa647ff3c36cfab592509e13860ab8c4f28781a66",
   "nonce": 1,
   "value": "0x0",
   "gasLimit": 12500000,
   "gasPrice": "0x1",
   "gasFeeCap": "0x0",
   "gasTipCap": "0x0",
   "data": "0xfbb2a4c2edc998034d71996986f41768bcfa20222c37679acdafac5fed378ea1271bfb70",
   "dataAbiValues": {
    "methodSignature": "test_UserDepositsInVault(uint256)",
    "inputValues": [
     "107554330528734919948020409272171343971518563101318177115271232138043964783472"
    ]
   },
   "AccessList": null,
   "SkipNonceChecks": true,
   "SkipFromEOACheck": true
  },
  "blockNumberDelay": 59135,
  "blockTimestampDelay": 555671
 }
]